LICENSE
MANIFEST.in
README.md
megaparsex.py
megaparsex_example_1.py
setup.py
megaparsex.egg-info/PKG-INFO
megaparsex.egg-info/SOURCES.txt
megaparsex.egg-info/dependency_links.txt
megaparsex.egg-info/entry_points.txt
megaparsex.egg-info/requires.txt
megaparsex.egg-info/top_level.txt