Metadata-Version: 1.0
Name: megaparsex
Version: 2017.10.4.2347
Summary: parsing and associated utilities
Home-page: https://github.com/wdbm/megaparsex
Author: Will Breaden Madden
Author-email: wbm@protonmail.ch
License: GPLv3
Platform: UNKNOWN
